{
  "year": "2010",
  "month": "01",
  "day": "29",
  "comments": [
    {
      "id": "2434",
      "author": "Adriana",
      "timestamp": "2010-01-29T20:11:51Z",
      "body": "Frenz!! You guys are awesome. Thanks so much for coming out to my defense (yes, I passed...!). It was so nice having such great friendly peeps in the audience. Rock on! -Adriana"
    },
    {
      "id": "2435",
      "author": "Dave",
      "timestamp": "2010-01-29T20:55:10Z",
      "body": "Hey Adriana, You were outstanding this morning... Great, great job! We knew in the first 5 minutes that you would pass. Congratulations!! DU"
    }
  ]
}